LICENSE
MANIFEST.in
NOTICE.md
README.md
requirements-docs.txt
requirements-extra-cli.txt
requirements-extra-image.txt
requirements-test.txt
requirements.txt
setup.py
tox.ini
steenzout/__init__.py
steenzout.barcode.egg-info/PKG-INFO
steenzout.barcode.egg-info/SOURCES.txt
steenzout.barcode.egg-info/dependency_links.txt
steenzout.barcode.egg-info/entry_points.txt
steenzout.barcode.egg-info/namespace_packages.txt
steenzout.barcode.egg-info/requires.txt
steenzout.barcode.egg-info/top_level.txt
steenzout/barcode/__init__.py
steenzout/barcode/base.py
steenzout/barcode/codex.py
steenzout/barcode/ean.py
steenzout/barcode/errors.py
steenzout/barcode/factory.py
steenzout/barcode/helpers.py
steenzout/barcode/isxn.py
steenzout/barcode/metadata.py
steenzout/barcode/upc.py
steenzout/barcode/writer.py
steenzout/barcode/charsets/__init__.py
steenzout/barcode/charsets/code128.py
steenzout/barcode/charsets/code39.py
steenzout/barcode/charsets/ean.py
steenzout/barcode/charsets/upc.py
steenzout/barcode/cli/__init__.py
steenzout/barcode/fonts/DejaVuSansMono.ttf
tests/barcode_test.py
tests/unit/base_test.py
tests/unit/cli_test.py
tests/unit/ean_test.py
tests/unit/factory_test.py
tests/unit/package_test.py
tests/unit/upc_test.py